cdsutils/__init__.py
cdsutils/__main__.py
cdsutils/_util.py
cdsutils/_version.py
cdsutils/audio.py
cdsutils/avg.py
cdsutils/errors.py
cdsutils/feutils.py
cdsutils/fft.py
cdsutils/getdata.py
cdsutils/gnuradio_blocks.py
cdsutils/matrix.py
cdsutils/nds.py
cdsutils/plot.py
cdsutils/read.py
cdsutils/read_filter.py
cdsutils/servo.py
cdsutils/sfm.py
cdsutils/step.py
cdsutils/switch.py
cdsutils/test_commands.py
cdsutils/trigservo.py
cdsutils/water.py
cdsutils/write.py
cdsutils-1.7.0.dist-info/COPYING
cdsutils-1.7.0.dist-info/COPYING-GPL-3
cdsutils-1.7.0.dist-info/METADATA
cdsutils-1.7.0.dist-info/WHEEL
cdsutils-1.7.0.dist-info/entry_points.txt
cdsutils-1.7.0.dist-info/top_level.txt
cdsutils-1.7.0.dist-info/RECORD
