Metadata-Version: 2.1
Name: cdsutils
Version: 1.7.0
Summary: Advanced LIGO CDS python utilities
Home-page: https://git.ligo.org/cds/cdsutils
Author: Jameson Graef Rollins
Author-email: jameson.rollins@ligo.org
License: GPL-3.0-or-later
Classifier: Development Status :: 5 - Production/Stable
Classifier: License :: OSI Approved :: GNU General Public License v3 or later (GPLv3+)
Classifier: Natural Language :: English
Classifier: Operating System :: OS Independent
Classifier: Programming Language :: Python
Classifier: Programming Language :: Python :: 3.5
Classifier: Programming Language :: Python :: 3.6
Classifier: Programming Language :: Python :: 3.7
License-File: COPYING
License-File: COPYING-GPL-3
Requires-Dist: gpstime
Requires-Dist: matplotlib
Requires-Dist: numpy
Requires-Dist: ezca
